expert_llm/__init__.py
expert_llm/api.py
expert_llm/cached_embedder.py
expert_llm/models.py
expert_llm/py.typed
expert_llm/remote/__init__.py
expert_llm/remote/jina_ai_client.py
expert_llm/remote/openai_shaped_client.py
expert_llm/remote/openai_shaped_client_implementations.py
expert_llm/tools/__init__.py
expert_llm/tools/analyze_requests.py
expert_llm-0.1.9.dist-info/METADATA
expert_llm-0.1.9.dist-info/WHEEL
expert_llm-0.1.9.dist-info/top_level.txt
expert_llm-0.1.9.dist-info/RECORD
